{
  "realm": "jimm",
  "enabled": true,
  "loginWithEmailAllowed": true,
  "duplicateEmailsAllowed": false,
  "registrationAllowed": false,
  "resetPasswordAllowed": false,
  "oauth2DevicePollingInterval": 1,
  "users": [
    {
      "username": "jimm-test",
      "email": "jimm-test@canonical.com",
      "emailVerified": true,
      "enabled": true,
      "credentials": [
        {
          "type": "password",
          "value": "password",
          "temporary": false
        }
      ]
    },
    {
      "username": "jimm-user",
      "email": "jimm-user@canonical.com",
      "emailVerified": true,
      "enabled": true,
      "credentials": [
        {
          "type": "password",
          "value": "password",
          "temporary": false
        }
      ]
    },
    {
      "username": "jimm_test",
      "email": "jimm_test@canonical.com",
      "emailVerified": true,
      "enabled": true,
      "credentials": [
        {
          "type": "password",
          "value": "password",
          "temporary": false
        }
      ]
    },
    {
      "id": "jimm-group-user-id",
      "username": "jimm-group-user",
      "email": "jimm-group-user@canonical.com",
      "emailVerified": true,
      "enabled": true,
      "groups": [
        "/canonical"
      ],
      "credentials": [
        {
          "type": "password",
          "value": "password",
          "temporary": false
        }
      ]
    },
    {
      "id": "123e4567-e89b-12d3-a456-426614174000",
      "username": "service-account-test-client-id-with-groups",
      "enabled": true,
      "serviceAccountClientId": "test-client-id-with-groups",
      "groups": [
        "/canonical"
      ]
    }
  ],
  "groups": [
    {
      "name": "canonical"
    }
  ],
  "clients": [
    {
      "clientId": "test-client-id",
      "name": "JIMM test service account",
      "protocol": "openid-connect",
      "enabled": true,
      "clientAuthenticatorType": "client-secret",
      "secret": "2M2blFbO4GX4zfggQpivQSxwWX1XGgNf",
      "publicClient": false,
      "serviceAccountsEnabled": true,
      "standardFlowEnabled": false,
      "directAccessGrantsEnabled": false,
      "fullScopeAllowed": true,
      "optionalClientScopes": [
        "group"
      ]
    },
    {
      "clientId": "test-client-id-with-groups",
      "name": "JIMM test service account with groups",
      "protocol": "openid-connect",
      "enabled": true,
      "clientAuthenticatorType": "client-secret",
      "secret": "d6JVj6NDXYx56muG6ZmjWMLcJnIYQjD0",
      "publicClient": false,
      "serviceAccountsEnabled": true,
      "standardFlowEnabled": false,
      "directAccessGrantsEnabled": false,
      "fullScopeAllowed": true,
      "optionalClientScopes": [
        "group"
      ]
    },
    {
      "clientId": "jimm-device",
      "name": "JIMM local browser and device flow client",
      "description": "Client used by the local JIMM environment",
      "protocol": "openid-connect",
      "enabled": true,
      "clientAuthenticatorType": "client-secret",
      "secret": "SwjDofnbDzJDm9iyfUhEp67FfUFMY8L4",
      "publicClient": false,
      "standardFlowEnabled": true,
      "directAccessGrantsEnabled": true,
      "serviceAccountsEnabled": false,
      "fullScopeAllowed": true,
      "defaultClientScopes": [
        "profile",
        "email"
      ],
      "optionalClientScopes": [
        "group"
      ],
      "redirectUris": [
        "http://127.0.0.1/*",
        "https://jimm.localhost/*",
        "https://localhost/*"
      ],
      "webOrigins": [
        "*"
      ],
      "attributes": {
        "login_theme": "base",
        "oauth2.device.authorization.grant.enabled": "true"
      }
    }
  ],
  "clientScopes": [
    {
      "name": "profile",
      "description": "OpenID Connect built-in scope: profile",
      "protocol": "openid-connect",
      "attributes": {
        "include.in.token.scope": "true",
        "display.on.consent.screen": "true"
      },
      "protocolMappers": []
    },
    {
      "name": "email",
      "description": "OpenID Connect built-in scope: email",
      "protocol": "openid-connect",
      "attributes": {
        "include.in.token.scope": "true",
        "display.on.consent.screen": "true"
      },
      "protocolMappers": [
        {
          "name": "email",
          "protocol": "openid-connect",
          "protocolMapper": "oidc-usermodel-property-mapper",
          "consentRequired": false,
          "config": {
            "introspection.token.claim": "true",
            "userinfo.token.claim": "true",
            "user.attribute": "email",
            "id.token.claim": "true",
            "access.token.claim": "true",
            "claim.name": "email",
            "jsonType.label": "String"
          }
        }
      ]
    },
    {
      "name": "group",
      "description": "The organisational group a user belongs to.",
      "protocol": "openid-connect",
      "attributes": {
        "include.in.token.scope": "true",
        "display.on.consent.screen": "false"
      },
      "protocolMappers": [
        {
          "name": "groups",
          "protocol": "openid-connect",
          "protocolMapper": "oidc-group-membership-mapper",
          "consentRequired": false,
          "config": {
            "introspection.token.claim": "true",
            "multivalued": "true",
            "userinfo.token.claim": "true",
            "id.token.claim": "false",
            "access.token.claim": "true",
            "claim.name": "groups",
            "full.path": "false",
            "jsonType.label": "String"
          }
        }
      ]
    }
  ]
}
